data/docker-compose.yml
data/nginx.conf
extract/__init__.py
extract/common.py
extract/docker.py
extract/podman.py
husk_cli-0.1.0.dist-info/LICENSE
husk_cli-0.1.0.dist-info/METADATA
husk_cli-0.1.0.dist-info/WHEEL
husk_cli-0.1.0.dist-info/entry_points.txt
husk_cli-0.1.0.dist-info/top_level.txt
husk_cli-0.1.0.dist-info/RECORD
