Metadata-Version: 2.1
Name: husk-cli
Version: 0.1.0
Summary: A tool for building ~10x smaller, self-hostable, read-only container registries
Author: dosisod
License: MIT
Project-URL: Source, https://github.com/vivid-sh/husk
Classifier: Intended Audience :: Developers
Classifier: License :: OSI Approved :: MIT License
Classifier: Typing :: Typed
Requires-Python: >=3.10
License-File: LICENSE
Requires-Dist: httpx >=0.27.0
